pysweet/__init__.py
pysweet/expression.py
pysweet/func.py
pysweet/iterable.py
pysweet/py.typed
pysweet/types.py
pysweet/value.py
pysweet_func-1.1.9.dist-info/LICENSE
pysweet_func-1.1.9.dist-info/WHEEL
pysweet_func-1.1.9.dist-info/METADATA
pysweet_func-1.1.9.dist-info/RECORD
