Metadata-Version: 2.1
Name: pysweet-func
Version: 1.1.9
Summary: Composable Python via syntactic sugar
Home-page: https://github.com/natso26/pysweet-func
License: MIT
Keywords: utility,functional
Author: Nat Sothanaphan
Author-email: natsothanaphan@gmail.com
Requires-Python: >=3.8,<4.0
Classifier: Development Status :: 5 - Production/Stable
Classifier: Intended Audience :: Developers
Classifier: License :: OSI Approved :: MIT License
Classifier: Natural Language :: English
Classifier: Operating System :: OS Independent
Classifier: Programming Language :: Python :: 3
Classifier: Programming Language :: Python :: 3.8
Classifier: Programming Language :: Python :: 3.9
Classifier: Programming Language :: Python :: 3.10
Classifier: Programming Language :: Python :: 3.11
Classifier: Programming Language :: Python :: 3.8
Classifier: Topic :: Software Development :: Libraries :: Python Modules
Classifier: Topic :: Utilities
Project-URL: Documentation, https://pysweet-func.readthedocs.io
Project-URL: Repository, https://github.com/natso26/pysweet-func
